src/__init__.py
src/book.py
src/categories/__init__.py
src/categories/biography.py
src/categories/history.py
src/categories/science.py
src/categories/selfimprovement.py
src/categories/travel.py
src/exceptions/__init__.py
src/utils/__init__.py
src/utils/utils.py
bookgpt-0.6.2.1.dist-info/LICENSE
bookgpt-0.6.2.1.dist-info/METADATA
bookgpt-0.6.2.1.dist-info/WHEEL
bookgpt-0.6.2.1.dist-info/top_level.txt
bookgpt-0.6.2.1.dist-info/RECORD
