Metadata-Version: 2.1
Name: bookgpt
Version: 0.6.2.1
Summary: Generating books using OpenAI's GPT-3 API.
Author: Mika Vehns
Author-email: <mika.vehns@outlook.com>
Keywords: python,gpt-3,openai,book,generator,writer
Classifier: Development Status :: 5 - Production/Stable
Classifier: Intended Audience :: Developers
Classifier: Programming Language :: Python :: 3
Classifier: Operating System :: OS Independent
License-File: LICENSE
Requires-Dist: openai
Requires-Dist: markdown
Requires-Dist: retrying
